<?xml version="1.0"?>
<!DOCTYPE hibernate-mapping PUBLIC "-//Hibernate/Hibernate Mapping DTD 3.0//EN"
"http://www.hibernate.org/dtd/hibernate-mapping-3.0.dtd">
<!-- Generated Nov 23, 2016 2:43:19 PM by Hibernate Tools 4.3.1 -->
<hibernate-mapping>
    <class name="Hibernate.Mahasiswa" table="mahasiswa" schema="public" optimistic-lock="version">
        <id name="nim" type="string">
            <column name="nim" length="20" />
            <generator class="assigned" />
        </id>
        <property name="namamhs" type="string">
            <column name="namamhs" not-null="true" />
        </property>
        <property name="fakultas" type="string">
            <column name="fakultas" length="50" not-null="true" />
        </property>
        <property name="prodi" type="string">
            <column name="prodi" length="50" not-null="true" />
        </property>
        <property name="telahmhs" type="string">
            <column name="telahmhs" not-null="true" />
        </property>
        <property name="talahmhs" type="date">
            <column name="talahmhs" length="13" not-null="true" />
        </property>
        <property name="jkmhs" type="string">
            <column name="jkmhs" length="10" not-null="true" />
        </property>
        <property name="statusmhs" type="string">
            <column name="statusmhs" not-null="true" />
        </property>
        <property name="alamatmhs" type="string">
            <column name="alamatmhs" not-null="true" />
        </property>
        <property name="npmhs" type="string">
            <column name="npmhs" />
        </property>
    </class>
</hibernate-mapping>
